myerson/__init__.py
myerson/myerson.py
myerson/myerson_explain.py
myerson-0.1.8.dist-info/WHEEL
myerson-0.1.8.dist-info/METADATA
myerson-0.1.8.dist-info/RECORD
