Metadata-Version: 2.1
Name: myerson
Version: 0.1.8
Summary: A python package to calculate Myerson values from game theory and use them as explanations for graph neural networks.
Author-email: "Samuel K. R. Homberg" <samuel.homberg@uni-muenster.de>
Requires-Python: >=3.8
Classifier: Programming Language :: Python :: 3
Classifier: License :: OSI Approved :: MIT License
Classifier: Operating System :: OS Independent
Requires-Dist: tqdm
Requires-Dist: numpy >= 1.25, < 2
Requires-Dist: networkx >= 3.1
Requires-Dist: sphinx_rtd_theme ; extra == "docs"
Requires-Dist: sphinx ; extra == "docs"
Requires-Dist: torch_geometric >= 2.3.1, < 3 ; extra == "explain"
Requires-Dist: torch >= 2.0.1, < 3 ; extra == "explain"
Requires-Dist: pytest ; extra == "test"
Project-URL: Documentation, https://myerson.readthedocs.io/en/latest/
Project-URL: Source, https://github.com/kochgroup/myerson
Provides-Extra: docs
Provides-Extra: explain
Provides-Extra: test
